attr_utils/__init__.py
attr_utils/annotations.py
attr_utils/autoattrs.py
attr_utils/docstrings.py
attr_utils/mypy_plugin.py
attr_utils/pprinter.py
attr_utils/py.typed
attr_utils/serialise.py
attr_utils/utils.py
attr_utils-1.1.0.dist-info/LICENSE
attr_utils-1.1.0.dist-info/METADATA
attr_utils-1.1.0.dist-info/WHEEL
attr_utils-1.1.0.dist-info/entry_points.txt
attr_utils-1.1.0.dist-info/RECORD
